federpy/__init__.py
federpy/federpy.py
federpy-0.8.0.dist-info/LICENSE
federpy-0.8.0.dist-info/METADATA
federpy-0.8.0.dist-info/WHEEL
federpy-0.8.0.dist-info/top_level.txt
federpy-0.8.0.dist-info/RECORD
