Metadata-Version: 2.1
Name: federpy
Version: 0.8.0
Summary: Feder for python
Home-page: https://github.com/zilliztech/feder
Author: min.tian@zilliz
Author-email: min.tian@zilliz.com
Classifier: Programming Language :: Python :: 3
Classifier: License :: OSI Approved :: MIT License
Classifier: Operating System :: OS Independent
Requires-Python: >=3.6
License-File: LICENSE
